MANIFEST.in
README.md
setup.py
django_qoptions.egg-info/PKG-INFO
django_qoptions.egg-info/SOURCES.txt
django_qoptions.egg-info/dependency_links.txt
django_qoptions.egg-info/not-zip-safe
django_qoptions.egg-info/top_level.txt
options/__init__.py
options/admin.py
options/functions.py
options/models.py
options/options_settings.py
options/translation.py
options/locale/en/LC_MESSAGES/django.mo
options/locale/en/LC_MESSAGES/django.po
options/locale/lv/LC_MESSAGES/django.mo
options/locale/lv/LC_MESSAGES/django.po
options/locale/ru/LC_MESSAGES/django.mo
options/locale/ru/LC_MESSAGES/django.po
options/templatetags/__init__.py
options/templatetags/options.py