Metadata-Version: 2.1
Name: django-qoptions
Version: 0.2.0
Summary: Options, Labels and standalone Texts for django admin. Administrator emails, phones, contact data, etc.
Home-page: https://github.com/Brick85/options/
Author: Vital Belikov
Author-email: vital@qwe.lv
License: New BSD
Platform: UNKNOWN
Classifier: Development Status :: 5 - Production/Stable
Classifier: Environment :: Web Environment
Classifier: Framework :: Django
Classifier: Intended Audience :: Developers
Classifier: License :: OSI Approved :: BSD License
Classifier: Natural Language :: English
Classifier: Operating System :: Unix
Classifier: Programming Language :: Python :: 3
Classifier: Topic :: Utilities
Requires: django(>=4.0)
